vayuayan/__init__.py
vayuayan/__main__.py
vayuayan/air_quality_client.py
vayuayan/cli.py
vayuayan/client.py
vayuayan/commands.py
vayuayan/constants.py
vayuayan/exceptions.py
vayuayan/utils.py
vayuayan-0.1.3.dist-info/licenses/LICENSE
vayuayan-0.1.3.dist-info/METADATA
vayuayan-0.1.3.dist-info/WHEEL
vayuayan-0.1.3.dist-info/entry_points.txt
vayuayan-0.1.3.dist-info/top_level.txt
vayuayan-0.1.3.dist-info/RECORD
