Metadata-Version: 2.4
Name: vayuayan
Version: 0.1.3
Summary: Package for fetching and analyzing air quality data from multiple sources
Author-email: Saket Choudhary <saketc@iitb.ac.in>, Mahesh Kumar Prajapat <22b0433@iitb.ac.in>
Maintainer-email: Saket Choudhary <saketc@iitb.ac.in>, Mahesh Kumar Prajapat <22b0433@iitb.ac.in>
License-Expression: MIT
Project-URL: Homepage, https://github.com/saketlab/vayuayan
Project-URL: Repository, https://github.com/saketlab/vayuayan.git
Project-URL: Documentation, https://saketlab.github.io/vayuayan
Project-URL: Bug Tracker, https://github.com/saketlab/vayuayan/issues
Classifier: Development Status :: 3 - Alpha
Classifier: Intended Audience :: Developers
Classifier: Operating System :: OS Independent
Classifier: Programming Language :: Python :: 3
Classifier: Programming Language :: Python :: 3.9
Classifier: Programming Language :: Python :: 3.10
Classifier: Programming Language :: Python :: 3.11
Classifier: Programming Language :: Python :: 3.12
Classifier: Programming Language :: Python :: 3.13
Classifier: Topic :: Scientific/Engineering :: Atmospheric Science
Classifier: Topic :: Internet :: WWW/HTTP :: Dynamic Content
Requires-Python: >=3.9
License-File: LICENSE
Requires-Dist: requests>=2.25.0
Requires-Dist: pandas>=1.3.0
Requires-Dist: openpyxl==3.1.5
Requires-Dist: urllib3>=1.26.0
Requires-Dist: geopandas>=1.0.1
Requires-Dist: geopy>=2.4.1
Requires-Dist: rioxarray>=0.15.0
Requires-Dist: xarray>=2024.7.0
Requires-Dist: netCDF4>=1.7.2
Requires-Dist: tqdm>=4.62.0
Provides-Extra: dev
Requires-Dist: pytest>=6.0; extra == "dev"
Requires-Dist: pytest-cov; extra == "dev"
Requires-Dist: black; extra == "dev"
Requires-Dist: flake8; extra == "dev"
Requires-Dist: mypy; extra == "dev"
Requires-Dist: pre-commit; extra == "dev"
Provides-Extra: docs
Requires-Dist: myst-nb>=1.3.0; extra == "docs"
Requires-Dist: sphinx>=8.2.3; extra == "docs"
Requires-Dist: furo>=2024.8.6; extra == "docs"
Requires-Dist: sphinx-multiversion>=0.2.4; extra == "docs"
Provides-Extra: notebooks
Requires-Dist: jupyter; extra == "notebooks"
Requires-Dist: matplotlib; extra == "notebooks"
Requires-Dist: seaborn; extra == "notebooks"
Dynamic: license-file
